pypuf/__init__.py
pypuf/batch.py
pypuf/io.py
pypuf/random.py
pypuf/attack/__init__.py
pypuf/attack/base.py
pypuf/attack/fourier.py
pypuf/attack/linear_regression.py
pypuf/attack/lr2021.py
pypuf/attack/mlp2021.py
pypuf/attack/regression.py
pypuf/metrics/__init__.py
pypuf/metrics/common.py
pypuf/metrics/fourier.py
pypuf/metrics/optical.py
pypuf/simulation/__init__.py
pypuf/simulation/base.py
pypuf/simulation/bistable.py
pypuf/simulation/delay.py
pypuf/simulation/optical.py
test/__init__.py
pypuf-3.2.1.dist-info/LICENSE.txt
pypuf-3.2.1.dist-info/METADATA
pypuf-3.2.1.dist-info/WHEEL
pypuf-3.2.1.dist-info/top_level.txt
pypuf-3.2.1.dist-info/RECORD
