Metadata-Version: 2.1
Name: pypuf
Version: 3.2.1
Summary: UNKNOWN
Home-page: https://github.com/nils-wisiol/pypuf
Maintainer: Nils Wisiol
Maintainer-email: pypuf@nils-wisiol.de
License: GNU General Public License Version 3
Platform: UNKNOWN
Requires-Dist: memory-profiler
Requires-Dist: more-itertools
Requires-Dist: numpy (>=1.18)
Requires-Dist: scipy (>=1.5)
Requires-Dist: tensorflow (~=2.4.0)
